{
  "resource": {
    "resourceType": "Organization",
    "id": "c093edf67777e638e482a1ea8e92182ef2af444e5b6e3f0b6b9bceddf1d5c9c3",
    "identifier": [
      {
        "system": "https://fhir.greenwayhealth.io/oid",
        "value": "2.16.840.1.113883.3.140.71895"
      }
    ],
    "active": true,
    "name": "Pain Management & Orthopedic Center, PC",
    "address": [
      {
        "line": [
          "5320 Providence Road",
          "Suite 204"
        ],
        "city": "Virginia Beach",
        "state": "VA",
        "postalCode": "23464"
      }
    ],
    "endpoint": [
      {
        "reference": "Endpoint/6ba9ecb50a654879f7007b8dc247415f966f1eea2731258082b0b03174232995"
      }
    ]
  },
  "fullUrl": "https://fhir-api.fhirprod.aws.greenwayhealth.com/fhir/R4/2.16.840.1.113883.3.140.71895/Organization/c093edf67777e638e482a1ea8e92182ef2af444e5b6e3f0b6b9bceddf1d5c9c3"
}