{
  "resource": {
    "resourceType": "Organization",
    "id": "8a72da7c-e99d-5592-9ef6-eeb9c0472243",
    "name": "JACOBS WELL",
    "endpoint": [
      {
        "reference": "Endpoint/27a4e967-47aa-5a9c-a572-b8297ee268a2"
      },
      {
        "reference": "Endpoint/b613a46f-9df6-5676-ab6d-c264d32cd320"
      }
    ],
    "identifier": [
      {
        "system": "http://hl7.org/fhir/sid/us-npi",
        "value": "1962620658"
      }
    ],
    "address": [
      {
        "line": [
          "522 THOMAS RUN ROAD"
        ],
        "city": "BEL AIR",
        "state": "MD",
        "postalCode": "21015-1621"
      }
    ],
    "extension": [
      {
        "url": "https://fhir.athena.io/StructureDefinition/ah-practice",
        "valueReference": {
          "reference": "Organization/a-1.Practice-11659"
        }
      },
      {
        "url": "https://fhir.athena.io/StructureDefinition/ah-brand",
        "valueReference": {
          "reference": "Organization/a-11659.Brand-1"
        }
      }
    ]
  },
  "fullUrl": "urn:uuid:8a72da7c-e99d-5592-9ef6-eeb9c0472243"
}