{
  "resource": {
    "resourceType": "Organization",
    "id": "e823d729-b036-5fbc-98a5-5de4387de6f6",
    "name": "White Oaks Rehabilitation and Nursing Center",
    "endpoint": [
      {
        "reference": "Endpoint/27a4e967-47aa-5a9c-a572-b8297ee268a2"
      },
      {
        "reference": "Endpoint/a44d0183-0a8a-58bc-b739-be759a9211db"
      }
    ],
    "identifier": [
      {
        "system": "http://hl7.org/fhir/sid/us-npi",
        "value": "1144376880"
      }
    ],
    "address": [
      {
        "line": [
          "8565 Jericho Tpke"
        ],
        "city": "WOODBURY",
        "state": "NY",
        "postalCode": "11797-1804"
      }
    ],
    "extension": [
      {
        "url": "https://fhir.athena.io/StructureDefinition/ah-practice",
        "valueReference": {
          "reference": "Organization/a-1.Practice-10566"
        }
      },
      {
        "url": "https://fhir.athena.io/StructureDefinition/ah-brand",
        "valueReference": {
          "reference": "Organization/a-10566.Brand-1"
        }
      }
    ]
  },
  "fullUrl": "urn:uuid:e823d729-b036-5fbc-98a5-5de4387de6f6"
}