{
  "resource": {
    "resourceType": "Endpoint",
    "id": "6bdc7434-edb4-5e3e-bb55-bdea5376c4f7",
    "address": "https://api.platform.athenahealth.com/18900/brand/1/csg/1/fhir/r4",
    "status": "active",
    "payloadType": [
      {
        "text": "athenahealth FHIR Service Brand Base URL"
      }
    ],
    "connectionType": {
      "system": "http://terminology.hl7.org/CodeSystem/endpoint-connection-type",
      "code": "hl7-fhir-rest",
      "display": "HL7 FHIR"
    }
  },
  "fullUrl": "urn:uuid:6bdc7434-edb4-5e3e-bb55-bdea5376c4f7"
}