{
  "resource": {
    "resourceType": "Organization",
    "id": "39fc01e6-3134-533f-92d9-b0e2fe069922",
    "name": "Woodbriar Nursing home",
    "endpoint": [
      {
        "reference": "Endpoint/27a4e967-47aa-5a9c-a572-b8297ee268a2"
      },
      {
        "reference": "Endpoint/854c5b37-1b58-5bae-b8f0-c141c0f5fec6"
      }
    ],
    "identifier": [
      {
        "system": "http://hl7.org/fhir/sid/us-npi",
        "value": "1871575480"
      },
      {
        "system": "urn:oid:2.16.840.1.113883.4.7",
        "value": "22D0990272"
      }
    ],
    "address": [
      {
        "line": [
          "90 west st"
        ],
        "city": "WILMINGTON",
        "state": "MA",
        "postalCode": "01887-3039"
      }
    ],
    "extension": [
      {
        "url": "https://fhir.athena.io/StructureDefinition/ah-practice",
        "valueReference": {
          "reference": "Organization/a-1.Practice-106"
        }
      },
      {
        "url": "https://fhir.athena.io/StructureDefinition/ah-brand",
        "valueReference": {
          "reference": "Organization/a-106.Brand-1"
        }
      }
    ]
  },
  "fullUrl": "urn:uuid:39fc01e6-3134-533f-92d9-b0e2fe069922"
}