{
  "resource": {
    "resourceType": "Organization",
    "id": "f1e10794-5cb1-581a-b076-00526b22f905",
    "name": "Baptist East ER",
    "endpoint": [
      {
        "reference": "Endpoint/27a4e967-47aa-5a9c-a572-b8297ee268a2"
      },
      {
        "reference": "Endpoint/1c973d4f-dfe2-5c5f-964a-dc0193d5589b"
      }
    ],
    "identifier": [
      {
        "system": "http://hl7.org/fhir/sid/us-npi",
        "value": "1184061509"
      }
    ],
    "address": [
      {
        "line": [
          "6019 WALNUT GROVE"
        ],
        "city": "MEMPHIS",
        "state": "TN",
        "postalCode": "38120-2113"
      }
    ],
    "extension": [
      {
        "url": "https://fhir.athena.io/StructureDefinition/ah-practice",
        "valueReference": {
          "reference": "Organization/a-1.Practice-7458"
        }
      },
      {
        "url": "https://fhir.athena.io/StructureDefinition/ah-brand",
        "valueReference": {
          "reference": "Organization/a-7458.Brand-1"
        }
      }
    ]
  },
  "fullUrl": "urn:uuid:f1e10794-5cb1-581a-b076-00526b22f905"
}