{
  "resource": {
    "resourceType": "Organization",
    "id": "bcde35fd-afb6-5cbf-8662-c24d0c1761be",
    "name": "Faith Prosthetics Gastonia",
    "endpoint": [
      {
        "reference": "Endpoint/27a4e967-47aa-5a9c-a572-b8297ee268a2"
      },
      {
        "reference": "Endpoint/1122c15d-0b6f-5888-bdc3-5c50487ecf44"
      }
    ],
    "identifier": [
      {
        "system": "http://hl7.org/fhir/sid/us-npi",
        "value": "1215223862"
      }
    ],
    "address": [
      {
        "line": [
          "916 COX RD",
          "Suite 209"
        ],
        "city": "GASTONIA",
        "state": "NC",
        "postalCode": "28054-3496"
      }
    ],
    "extension": [
      {
        "url": "https://fhir.athena.io/StructureDefinition/ah-practice",
        "valueReference": {
          "reference": "Organization/a-1.Practice-4047"
        }
      },
      {
        "url": "https://fhir.athena.io/StructureDefinition/ah-brand",
        "valueReference": {
          "reference": "Organization/a-4047.Brand-1"
        }
      }
    ]
  },
  "fullUrl": "urn:uuid:bcde35fd-afb6-5cbf-8662-c24d0c1761be"
}