{
  "resource": {
    "resourceType": "Organization",
    "id": "e52a8c13-395c-594e-9114-326b03cba1c3",
    "name": "Woz Wellness",
    "endpoint": [
      {
        "reference": "Endpoint/27a4e967-47aa-5a9c-a572-b8297ee268a2"
      },
      {
        "reference": "Endpoint/4a287b47-be11-5e01-b6f5-56e95987605e"
      }
    ],
    "identifier": [
      {
        "system": "http://hl7.org/fhir/sid/us-npi",
        "value": "1851196075"
      }
    ],
    "address": [
      {
        "line": [
          "1397 MEDICAL PARK BLVD",
          "STE 140"
        ],
        "city": "WELLINGTON",
        "state": "FL",
        "postalCode": "33414-3187"
      }
    ],
    "extension": [
      {
        "url": "https://fhir.athena.io/StructureDefinition/ah-practice",
        "valueReference": {
          "reference": "Organization/a-1.Practice-32854"
        }
      },
      {
        "url": "https://fhir.athena.io/StructureDefinition/ah-brand",
        "valueReference": {
          "reference": "Organization/a-32854.Brand-1"
        }
      }
    ]
  },
  "fullUrl": "urn:uuid:e52a8c13-395c-594e-9114-326b03cba1c3"
}