{
  "resource": {
    "resourceType": "Organization",
    "id": "d498ddeb-7eb9-553f-8f6c-41e2d8a954c2",
    "name": "Bayou City Surgical Specialists - 720 West 11th Street",
    "endpoint": [
      {
        "reference": "Endpoint/27a4e967-47aa-5a9c-a572-b8297ee268a2"
      },
      {
        "reference": "Endpoint/0344bd9b-08ba-58fa-bb19-b8f730279693"
      }
    ],
    "identifier": [
      {
        "system": "http://hl7.org/fhir/sid/us-npi",
        "value": "1578969465"
      }
    ],
    "address": [
      {
        "line": [
          "720 WEST 11TH STREET"
        ],
        "city": "HOUSTON",
        "state": "TX",
        "postalCode": "77008-6714"
      }
    ],
    "extension": [
      {
        "url": "https://fhir.athena.io/StructureDefinition/ah-practice",
        "valueReference": {
          "reference": "Organization/a-1.Practice-8042"
        }
      },
      {
        "url": "https://fhir.athena.io/StructureDefinition/ah-brand",
        "valueReference": {
          "reference": "Organization/a-8042.Brand-1"
        }
      }
    ]
  },
  "fullUrl": "urn:uuid:d498ddeb-7eb9-553f-8f6c-41e2d8a954c2"
}