{
  "resource": {
    "resourceType": "Organization",
    "id": "1861172e-0d33-524e-a64f-ff498b1748d9",
    "name": "Marathon Health-St Peters MO-Mexico Rd",
    "endpoint": [
      {
        "reference": "Endpoint/27a4e967-47aa-5a9c-a572-b8297ee268a2"
      },
      {
        "reference": "Endpoint/35b6fd9f-056a-5a54-bdbf-c41e7d6eaab5"
      }
    ],
    "identifier": [
      {
        "system": "http://hl7.org/fhir/sid/us-npi",
        "value": "1043769722"
      }
    ],
    "address": [
      {
        "line": [
          "5700 MEXICO RD",
          "STE 16"
        ],
        "city": "SAINT PETERS",
        "state": "MO",
        "postalCode": "63376-1667"
      }
    ],
    "extension": [
      {
        "url": "https://fhir.athena.io/StructureDefinition/ah-practice",
        "valueReference": {
          "reference": "Organization/a-1.Practice-14940"
        }
      },
      {
        "url": "https://fhir.athena.io/StructureDefinition/ah-brand",
        "valueReference": {
          "reference": "Organization/a-14940.Brand-2"
        }
      }
    ]
  },
  "fullUrl": "urn:uuid:1861172e-0d33-524e-a64f-ff498b1748d9"
}