{
  "resource": {
    "resourceType": "Organization",
    "id": "c2ab87a9-8ae5-5384-a1db-97127e09ecd9",
    "name": "Border Kidney Specialists",
    "endpoint": [
      {
        "reference": "Endpoint/27a4e967-47aa-5a9c-a572-b8297ee268a2"
      },
      {
        "reference": "Endpoint/bab1e5ee-8446-5776-b847-37de8e505506"
      }
    ],
    "identifier": [
      {
        "system": "http://hl7.org/fhir/sid/us-npi",
        "value": "1801242458"
      }
    ],
    "address": [
      {
        "line": [
          "2270 JOE BATTLE BOULEVARD",
          "SUITE O"
        ],
        "city": "EL PASO",
        "state": "TX",
        "postalCode": "79938-2610"
      }
    ],
    "extension": [
      {
        "url": "https://fhir.athena.io/StructureDefinition/ah-practice",
        "valueReference": {
          "reference": "Organization/a-1.Practice-13852"
        }
      },
      {
        "url": "https://fhir.athena.io/StructureDefinition/ah-brand",
        "valueReference": {
          "reference": "Organization/a-13852.Brand-1"
        }
      }
    ]
  },
  "fullUrl": "urn:uuid:c2ab87a9-8ae5-5384-a1db-97127e09ecd9"
}