{
  "resource": {
    "resourceType": "Organization",
    "id": "cbfdd6ce-ddd5-4c51-9a2f-8a9d80c199c3",
    "identifier": [
      {
        "system": "http://fhir.developer.allscripts.com/systems/Pro/identifier",
        "value": "10028587"
      }
    ],
    "active": true,
    "name": "Orthopedic Assoc Of Dayton",
    "address": [
      {
        "line": [
          "7980 NORTH MAIN ST"
        ],
        "city": "Dayton",
        "state": "Ohio",
        "postalCode": "45415",
        "country": "US"
      }
    ],
    "endpoint": [
      {
        "reference": "Endpoint/8c36bfa9-4cc5-4c7e-bb22-eb213dec51c1"
      }
    ]
  },
  "fullUrl": "https://fhir.fhirpoint.open.allscripts.com/fhirroute/open/10028587/Organization/cbfdd6ce-ddd5-4c51-9a2f-8a9d80c199c3"
}