{
  "resource": {
    "resourceType": "Organization",
    "id": "a698b531-2d00-4c26-8095-502fe6c76824",
    "identifier": [
      {
        "system": "http://fhir.developer.allscripts.com/systems/Pro/identifier",
        "value": "10031743"
      }
    ],
    "active": true,
    "name": "Hackley Community Care Center",
    "address": [
      {
        "line": [
          "2700 BAKER ST 3RD FL"
        ],
        "city": "Muskegon Heights",
        "state": "Michigan",
        "postalCode": "49444",
        "country": "US"
      }
    ],
    "endpoint": [
      {
        "reference": "Endpoint/561e8d7b-e2c5-4940-8a02-44a2be9724b6"
      }
    ]
  },
  "fullUrl": "https://fhir.fhirpoint.open.allscripts.com/fhirroute/open/10031743/Organization/a698b531-2d00-4c26-8095-502fe6c76824"
}