{
  "resource": {
    "resourceType": "Endpoint",
    "id": "9562f063-15d5-4b76-b5f0-c9567e303ce7",
    "contained": [
      {
        "resourceType": "Organization",
        "id": "9562f063-15d5-4b76-b5f0-c9567e303ce7",
        "name": "The Wellbridge Group - Brighton, MI",
        "address": [
          {
            "line": [
              "10503 Citation Drive",
              "Suite #100"
            ],
            "city": "Brighton",
            "state": "MI",
            "postalCode": "48116",
            "country": "United States"
          }
        ]
      }
    ],
    "status": "active",
    "managingOrganization": {
      "id": "9562f063-15d5-4b76-b5f0-c9567e303ce7"
    },
    "address": "https://connect.pointclickcare.com/fhir/R4/9562f063-15d5-4b76-b5f0-c9567e303ce7/"
  }
}