{
  "resource": {
    "resourceType": "Organization",
    "id": "325820",
    "identifier": [
      {
        "system": "http://hl7.org/fhir/sid/us-npi",
        "value": "1043375611"
      }
    ],
    "active": true,
    "name": "NEUROLOGICAL DISORDERS CLINIC PA",
    "address": [
      {
        "line": [
          "880 NW 13TH ST",
          "SUITE 3-B"
        ],
        "city": "BOCA RATON",
        "state": "FL",
        "postalCode": "33486"
      }
    ],
    "endpoint": [
      {
        "reference": "Endpoint/EndPoint325820"
      }
    ]
  },
  "fullUrl": "https://api.enablemyhealth.com/api/r4/Organization/325820"
}