{
  "resource": {
    "resourceType": "Organization",
    "id": "2460041088",
    "meta": {
      "lastUpdated": "2024-12-31T06:31:31.263-05:00"
    },
    "text": {
      "status": "generated",
      "div": "<div xmlns=\"http://www.w3.org/1999/xhtml\">Shortgrass Community Health Center, Inc</div>"
    },
    "identifier": [
      {
        "system": "https://www.relimedsolutions.com",
        "value": "2460041088"
      },
      {
        "system": "http://hl7.org/fhir/sid/us-npi",
        "value": "1255695201"
      }
    ],
    "active": true,
    "name": "Shortgrass Community Health Center, Inc",
    "telecom": [
      {
        "system": "phone",
        "value": "580-688-2800",
        "use": "work",
        "rank": 1
      },
      {
        "system": "phone",
        "value": "580-688-2193",
        "use": "old",
        "rank": 2
      }
    ],
    "address": [
      {
        "extension": [
          {
            "extension": [
              {
                "url": "latitude",
                "valueDecimal": 35.0
              },
              {
                "url": "longitude",
                "valueDecimal": -100.0
              }
            ],
            "url": "http://hl7.org/fhir/StructureDefinition/geolocation"
          }
        ],
        "use": "billing",
        "line": [
          "PO Box 311"
        ],
        "city": "Hollis",
        "postalCode": "73550",
        "country": "US",
        "period": {
          "start": "2021-08-18"
        }
      },
      {
        "use": "work",
        "line": [
          "400 E SYCAMORE ST"
        ],
        "city": "HOLLIS",
        "postalCode": "735501436",
        "country": "US",
        "period": {
          "start": "2021-08-10"
        }
      }
    ],
    "endpoint": [
      {
        "reference": "Endpoint/10025680"
      }
    ]
  },
  "fullUrl": "https://interface.relimedsolutions.com/fhir/r4/Organization/2460041088"
}