{
  "resource": {
    "resourceType": "Organization",
    "id": "5b91539a-66cd-5d3e-b6b3-b9b6d7574e2b",
    "name": "McLean Internal Medicine - McLean",
    "endpoint": [
      {
        "reference": "Endpoint/27a4e967-47aa-5a9c-a572-b8297ee268a2"
      },
      {
        "reference": "Endpoint/0344bd9b-08ba-58fa-bb19-b8f730279693"
      }
    ],
    "identifier": [
      {
        "system": "http://hl7.org/fhir/sid/us-npi",
        "value": "1013042480"
      }
    ],
    "address": [
      {
        "line": [
          "1515 Chain Bridge Rd",
          "Suite 308"
        ],
        "city": "MC LEAN",
        "state": "VA",
        "postalCode": "22101-4421"
      }
    ],
    "extension": [
      {
        "url": "https://fhir.athena.io/StructureDefinition/ah-practice",
        "valueReference": {
          "reference": "Organization/a-1.Practice-8042"
        }
      },
      {
        "url": "https://fhir.athena.io/StructureDefinition/ah-brand",
        "valueReference": {
          "reference": "Organization/a-8042.Brand-1"
        }
      }
    ]
  },
  "fullUrl": "urn:uuid:5b91539a-66cd-5d3e-b6b3-b9b6d7574e2b"
}