{
  "resource": {
    "resourceType": "Organization",
    "id": "72ccacbf-0d70-5eca-814b-9793a1bb8b6b",
    "name": "Trinitas Physician Practice, L.L.C",
    "endpoint": [
      {
        "reference": "Endpoint/27a4e967-47aa-5a9c-a572-b8297ee268a2"
      },
      {
        "reference": "Endpoint/7e96e121-0eae-52ba-8ed2-e6d72ede500c"
      }
    ],
    "identifier": [
      {
        "system": "http://hl7.org/fhir/sid/us-npi",
        "value": "1205189941"
      }
    ],
    "address": [
      {
        "line": [
          "67 Westfield Ave"
        ],
        "city": "CLARK",
        "state": "NJ",
        "postalCode": "07066-3216"
      }
    ],
    "extension": [
      {
        "url": "https://fhir.athena.io/StructureDefinition/ah-practice",
        "valueReference": {
          "reference": "Organization/a-1.Practice-3830"
        }
      },
      {
        "url": "https://fhir.athena.io/StructureDefinition/ah-brand",
        "valueReference": {
          "reference": "Organization/a-3830.Brand-5"
        }
      }
    ]
  },
  "fullUrl": "urn:uuid:72ccacbf-0d70-5eca-814b-9793a1bb8b6b"
}