{
  "resource": {
    "resourceType": "Organization",
    "id": "cd21bcf8-3503-5bc4-af16-b4c3a65c6af7",
    "name": "A PLUS OPERATIONAL SERVICES",
    "endpoint": [
      {
        "reference": "Endpoint/27a4e967-47aa-5a9c-a572-b8297ee268a2"
      },
      {
        "reference": "Endpoint/c622d8dc-3a1b-5860-a11a-8da302981d44"
      }
    ],
    "identifier": [
      {
        "system": "http://hl7.org/fhir/sid/us-npi",
        "value": "1750654240"
      }
    ],
    "address": [
      {
        "line": [
          "21216 NORTHWEST FREEWAY",
          "SUITE 250"
        ],
        "city": "CYPRESS",
        "state": "TX",
        "postalCode": "77429-4778"
      }
    ],
    "extension": [
      {
        "url": "https://fhir.athena.io/StructureDefinition/ah-practice",
        "valueReference": {
          "reference": "Organization/a-1.Practice-8008"
        }
      },
      {
        "url": "https://fhir.athena.io/StructureDefinition/ah-brand",
        "valueReference": {
          "reference": "Organization/a-8008.Brand-1"
        }
      }
    ]
  },
  "fullUrl": "urn:uuid:cd21bcf8-3503-5bc4-af16-b4c3a65c6af7"
}