{
  "resource": {
    "resourceType": "Organization",
    "id": "2825fd33-3f1c-51fc-8bdf-e1361bd628ec",
    "name": "Littleton Adventist Hospital",
    "endpoint": [
      {
        "reference": "Endpoint/27a4e967-47aa-5a9c-a572-b8297ee268a2"
      },
      {
        "reference": "Endpoint/6282ff64-fffd-52e9-b39f-148dad23cd01"
      }
    ],
    "identifier": [
      {
        "system": "http://hl7.org/fhir/sid/us-npi",
        "value": "1659435584"
      }
    ],
    "address": [
      {
        "line": [
          "7700 South Broadway"
        ],
        "city": "LITTLETON",
        "state": "CO",
        "postalCode": "80122-2602"
      }
    ],
    "extension": [
      {
        "url": "https://fhir.athena.io/StructureDefinition/ah-practice",
        "valueReference": {
          "reference": "Organization/a-1.Practice-15231"
        }
      },
      {
        "url": "https://fhir.athena.io/StructureDefinition/ah-brand",
        "valueReference": {
          "reference": "Organization/a-15231.Brand-1"
        }
      }
    ]
  },
  "fullUrl": "urn:uuid:2825fd33-3f1c-51fc-8bdf-e1361bd628ec"
}