{
  "resource": {
    "resourceType": "Organization",
    "id": "b2ad8579-4f07-5b5c-b28e-abb6be8a68d4",
    "name": "New Castle Office",
    "endpoint": [
      {
        "reference": "Endpoint/27a4e967-47aa-5a9c-a572-b8297ee268a2"
      },
      {
        "reference": "Endpoint/cf53ee5b-d261-59c0-8e07-3717d3800450"
      }
    ],
    "identifier": [
      {
        "system": "http://hl7.org/fhir/sid/us-npi",
        "value": "1649440256"
      }
    ],
    "address": [
      {
        "line": [
          "3212 WILMINGTON RD STE 20"
        ],
        "city": "NEW CASTLE",
        "state": "PA",
        "postalCode": "16105-1178"
      }
    ],
    "extension": [
      {
        "url": "https://fhir.athena.io/StructureDefinition/ah-practice",
        "valueReference": {
          "reference": "Organization/a-1.Practice-12985"
        }
      },
      {
        "url": "https://fhir.athena.io/StructureDefinition/ah-brand",
        "valueReference": {
          "reference": "Organization/a-12985.Brand-1"
        }
      }
    ]
  },
  "fullUrl": "urn:uuid:b2ad8579-4f07-5b5c-b28e-abb6be8a68d4"
}