{
  "resource": {
    "resourceType": "Organization",
    "id": "850087f9-28a7-548b-bc79-2b7a62def1a3",
    "name": "Bay Minette Family Care",
    "endpoint": [
      {
        "reference": "Endpoint/27a4e967-47aa-5a9c-a572-b8297ee268a2"
      },
      {
        "reference": "Endpoint/71ace3b6-af3c-50cf-b96a-c20d7cee1439"
      }
    ],
    "identifier": [
      {
        "system": "http://hl7.org/fhir/sid/us-npi",
        "value": "1588338248"
      }
    ],
    "address": [
      {
        "line": [
          "2012 HAND AVE"
        ],
        "city": "BAY MINETTE",
        "state": "AL",
        "postalCode": "36507-7649"
      }
    ],
    "extension": [
      {
        "url": "https://fhir.athena.io/StructureDefinition/ah-practice",
        "valueReference": {
          "reference": "Organization/a-1.Practice-25415"
        }
      },
      {
        "url": "https://fhir.athena.io/StructureDefinition/ah-brand",
        "valueReference": {
          "reference": "Organization/a-25415.Brand-1"
        }
      }
    ]
  },
  "fullUrl": "urn:uuid:850087f9-28a7-548b-bc79-2b7a62def1a3"
}