{
  "resource": {
    "resourceType": "Organization",
    "id": "3c087e10-6ed3-59a0-a852-d54f178f9920",
    "name": "The Pearl",
    "endpoint": [
      {
        "reference": "Endpoint/27a4e967-47aa-5a9c-a572-b8297ee268a2"
      },
      {
        "reference": "Endpoint/fce6b27f-21e3-5ded-b731-4ae0fed33e61"
      }
    ],
    "identifier": [
      {
        "system": "http://hl7.org/fhir/sid/us-npi",
        "value": "1235459686"
      }
    ],
    "address": [
      {
        "line": [
          "1701 NE 26th Street"
        ],
        "city": "Wilton Manors",
        "state": "FL",
        "postalCode": "33305-1412"
      }
    ],
    "extension": [
      {
        "url": "https://fhir.athena.io/StructureDefinition/ah-practice",
        "valueReference": {
          "reference": "Organization/a-1.Practice-17638"
        }
      },
      {
        "url": "https://fhir.athena.io/StructureDefinition/ah-brand",
        "valueReference": {
          "reference": "Organization/a-17638.Brand-1"
        }
      }
    ]
  },
  "fullUrl": "urn:uuid:3c087e10-6ed3-59a0-a852-d54f178f9920"
}