{
  "resource": {
    "resourceType": "Organization",
    "id": "0f7d9afb-940c-57c4-bcd0-32149b79b483",
    "name": "HILLSBORO MANOR NURSING HOME",
    "endpoint": [
      {
        "reference": "Endpoint/27a4e967-47aa-5a9c-a572-b8297ee268a2"
      },
      {
        "reference": "Endpoint/e74fb694-ac97-58df-b4d8-a41eea08d0ab"
      }
    ],
    "identifier": [
      {
        "system": "http://hl7.org/fhir/sid/us-npi",
        "value": "1427018704"
      }
    ],
    "address": [
      {
        "line": [
          "1700 E SHORT HILLSBORO ST"
        ],
        "city": "EL DORADO",
        "state": "AR",
        "postalCode": "71730-6458"
      }
    ],
    "extension": [
      {
        "url": "https://fhir.athena.io/StructureDefinition/ah-practice",
        "valueReference": {
          "reference": "Organization/a-1.Practice-2218"
        }
      },
      {
        "url": "https://fhir.athena.io/StructureDefinition/ah-brand",
        "valueReference": {
          "reference": "Organization/a-2218.Brand-1"
        }
      }
    ]
  },
  "fullUrl": "urn:uuid:0f7d9afb-940c-57c4-bcd0-32149b79b483"
}