{
  "resource": {
    "resourceType": "Organization",
    "id": "61dc68e66931ec03d",
    "identifier": [
      {
        "system": "http://hl7.org/fhir/StructureDefinition/data-absent-reason",
        "value": "unknown"
      }
    ],
    "active": true,
    "name": "Cratos Health",
    "address": [
      {
        "city": "Colorado Springs",
        "state": "CO",
        "country": "United States of America"
      }
    ],
    "endpoint": [
      {
        "reference": "Endpoint/VeracityEHR"
      }
    ]
  },
  "fullUrl": "https://fhir.allegiancemd.io/R4/Organization/61dc68e66931ec03d"
}