{
  "resource": {
    "resourceType": "Organization",
    "id": "352ea063-d81d-51e7-b47d-6cc9e01e6cb1",
    "meta": {
      "lastUpdated": "2024-11-19T17:48:10.000Z"
    },
    "identifier": [
      {
        "system": "urn:ietf:rfc:3986",
        "value": "https://mghwv.net"
      }
    ],
    "name": "Montgomery General Hospital",
    "active": true,
    "type": [
      {
        "coding": [
          {
            "system": "http://terminology.hl7.org/CodeSystem/organization-type",
            "code": "prov",
            "display": "Healthcare Provider"
          }
        ]
      }
    ],
    "telecom": [
      {
        "system": "url",
        "value": "https://mghwv.net"
      }
    ],
    "address": [
      {
        "line": [
          "401 6th Avenue"
        ],
        "city": "Montgomery",
        "state": "WV",
        "postalCode": "25136",
        "country": [
          "United",
          "States",
          " "
        ]
      }
    ],
    "endpoint": [
      {
        "reference": "urn:uuid:18cd94c4-be11-5f8d-843f-19401ff42f25"
      }
    ],
    "extension": [
      {
        "url": "http://hl7.org/fhir/StructureDefinition/organization-portal",
        "extension": [
          {
            "url": "portalEndpoint",
            "valueReference": {
              "reference": "urn:uuid:18cd94c4-be11-5f8d-843f-19401ff42f25"
            }
          }
        ]
      }
    ]
  },
  "fullUrl": "urn:uuid:352ea063-d81d-51e7-b47d-6cc9e01e6cb1"
}