{
  "resource": {
    "resourceType": "Organization",
    "id": "9fd8d64e-4056-42ff-a075-88ed6870fdc7",
    "meta": {
      "lastUpdated": "2025-08-06T17:50:18-05:00"
    },
    "active": true,
    "name": "WTMG PLASTICS SURGERY",
    "address": [
      {
        "type": "physical",
        "text": "569 Skyline Dr Suite 1\nJackson TN 38301-3911\nUnited States of America",
        "line": [
          "WTMG PLASTICS SURGERY",
          "569 Skyline Dr Suite 1"
        ],
        "city": "Jackson",
        "state": "TN",
        "postalCode": "38301-3911",
        "country": "US"
      }
    ],
    "partOf": {
      "reference": "urn:uuid:7f108326-1ebf-4e98-bad7-7de320007779"
    }
  },
  "fullUrl": "urn:uuid:9fd8d64e-4056-42ff-a075-88ed6870fdc7"
}