{
  "resource": {
    "resourceType": "Organization",
    "id": "e99abb92-1e92-4f55-bf5d-279fc0561aa4",
    "meta": {
      "lastUpdated": "2025-08-06T17:46:48-05:00"
    },
    "active": true,
    "name": "EC-IL CCH CHICAGO 1431 N WESTERN",
    "address": [
      {
        "type": "physical",
        "text": "1431 N Western Avenue\nCHICAGO IL 60622-1797\nUNITED STATES",
        "line": [
          "EC-IL CCH CHICAGO 1431 N WESTERN",
          "1431 N Western Avenue"
        ],
        "city": "CHICAGO",
        "state": "IL",
        "postalCode": "60622-1797",
        "country": "USA"
      }
    ],
    "partOf": {
      "reference": "urn:uuid:c961c1dd-8270-4f45-baf3-071552f2ebae"
    }
  },
  "fullUrl": "urn:uuid:e99abb92-1e92-4f55-bf5d-279fc0561aa4"
}