{
  "resource": {
    "resourceType": "Organization",
    "id": "d50a722d-2c15-47ed-986c-3ed9040e5cca",
    "meta": {
      "lastUpdated": "2024-09-06T19:06:13-05:00"
    },
    "active": true,
    "name": "QuadMed Effingham",
    "address": [
      {
        "type": "physical",
        "text": "1200 West Niccum Avenue\nEFFINGHAM IL 62401-4217\nUnited States of America",
        "line": [
          "QuadMed Effingham",
          "1200 West Niccum Avenue"
        ],
        "city": "EFFINGHAM",
        "state": "IL",
        "postalCode": "62401-4217",
        "country": "US"
      }
    ],
    "partOf": {
      "reference": "urn:uuid:5e9b9d32-4e78-42cc-92ad-3f50ecc18bbe"
    }
  },
  "fullUrl": "urn:uuid:d50a722d-2c15-47ed-986c-3ed9040e5cca"
}