{
  "resource": {
    "resourceType": "Organization",
    "id": "d26b7394-8533-4efe-ae2a-4e5af7b57689",
    "meta": {
      "lastUpdated": "2025-08-06T17:47:33-05:00"
    },
    "active": true,
    "name": "Portage Lakes Internal Medicine (prior to 10/29/22)",
    "address": [
      {
        "type": "physical",
        "text": "500 Portage Lake Dr Suite B\nAkron OH 44319\nUnited States of America",
        "line": [
          "Portage Lakes Internal Medicine (prior to 10/29/22)",
          "500 Portage Lake Dr Suite B"
        ],
        "city": "Akron",
        "state": "OH",
        "postalCode": "44319",
        "country": "USA"
      }
    ],
    "partOf": {
      "reference": "urn:uuid:c218f4cf-04a9-4f7e-b20a-effa30dc87bc"
    }
  },
  "fullUrl": "urn:uuid:d26b7394-8533-4efe-ae2a-4e5af7b57689"
}