{
  "resource": {
    "resourceType": "Organization",
    "id": "9659390b-7ce0-408d-95b1-2c48de2be459",
    "meta": {
      "lastUpdated": "2025-08-06T17:46:05-05:00"
    },
    "active": true,
    "name": "Cascade Orthopedic",
    "address": [
      {
        "type": "physical",
        "text": "328 S Stillaguamish Ave\nARLINGTON WA 98223-1642\nUnited States of America",
        "line": [
          "Cascade Orthopedic",
          "328 S Stillaguamish Ave"
        ],
        "city": "ARLINGTON",
        "state": "WA",
        "postalCode": "98223-1642",
        "country": "US"
      }
    ],
    "partOf": {
      "reference": "urn:uuid:60c3ede7-9244-424d-9c4c-d11d9098dc62"
    }
  },
  "fullUrl": "urn:uuid:9659390b-7ce0-408d-95b1-2c48de2be459"
}