{
  "resource": {
    "resourceType": "Organization",
    "id": "ea6cc6f7-3c01-429e-b5b3-f769d4ba84a9",
    "meta": {
      "lastUpdated": "2025-08-06T17:47:13-05:00"
    },
    "active": true,
    "name": "Atrium Health Navicent Primary Care - Monroe",
    "address": [
      {
        "type": "physical",
        "text": "120 N. Lee Street Suite A\nForsyth GA 31029\nUnited States of America",
        "line": [
          "Atrium Health Navicent Primary Care - Monroe",
          "120 N. Lee Street Suite A"
        ],
        "city": "Forsyth",
        "state": "GA",
        "postalCode": "31029",
        "country": "US"
      }
    ],
    "partOf": {
      "reference": "urn:uuid:02c51a84-2664-479a-9dc7-41ad45dcbd21"
    }
  },
  "fullUrl": "urn:uuid:ea6cc6f7-3c01-429e-b5b3-f769d4ba84a9"
}