{
  "resource": {
    "resourceType": "Organization",
    "id": "380337f2-2393-4866-b2f4-1616ffc5391b",
    "meta": {
      "lastUpdated": "2025-08-06T17:50:15-05:00"
    },
    "active": true,
    "name": "BSA Hospital",
    "address": [
      {
        "type": "physical",
        "text": "1600 Wallace Blvd, Amarillo, TX\nAmarillo TX 79106\nUnited States of America",
        "line": [
          "BSA Hospital",
          "1600 Wallace Blvd, Amarillo, TX"
        ],
        "city": "Amarillo",
        "state": "TX",
        "postalCode": "79106",
        "country": "US"
      }
    ],
    "partOf": {
      "reference": "urn:uuid:dc49ff5c-4e6e-4919-8244-853ea49f4684"
    }
  },
  "fullUrl": "urn:uuid:380337f2-2393-4866-b2f4-1616ffc5391b"
}