{
  "resource": {
    "resourceType": "Organization",
    "id": "3a5d1cc3-f487-4653-9b98-30d19a88930f",
    "meta": {
      "lastUpdated": "2025-08-06T17:46:05-05:00"
    },
    "active": true,
    "name": "The Christ Hospital Physicians - Heart & Vascular, Montgomery",
    "address": [
      {
        "type": "physical",
        "text": "11140 MONTGOMERY RD\nSTE 1300\nCINCINNATI OH 45249-2309\nUnited States of America",
        "line": [
          "The Christ Hospital Physicians - Heart & Vascular, Montgomery",
          "11140 MONTGOMERY RD\nSTE 1300"
        ],
        "city": "CINCINNATI",
        "state": "OH",
        "postalCode": "45249-2309",
        "country": "USA"
      }
    ],
    "partOf": {
      "reference": "urn:uuid:60d17a51-5976-49e7-b24c-108fa74130b7"
    }
  },
  "fullUrl": "urn:uuid:3a5d1cc3-f487-4653-9b98-30d19a88930f"
}