{
  "resource": {
    "resourceType": "Organization",
    "id": "ab404d4b-fea2-4270-be67-1943d5e5fbd9",
    "meta": {
      "lastUpdated": "2025-08-25T23:50:13-05:00"
    },
    "active": true,
    "name": "PACT - Orange - 250 Indian River",
    "address": [
      {
        "type": "physical",
        "text": "250 Indian River Rd\r\nSuite 300\r\nOrange CT 06477-3627\r\nUnited States of America",
        "line": [
          "PACT - Orange - 250 Indian River",
          "250 Indian River Rd\r\nSuite 300"
        ],
        "city": "Orange",
        "state": "CT",
        "postalCode": "06477-3627",
        "country": "US"
      }
    ],
    "partOf": {
      "reference": "urn:uuid:5c1766d0-2d39-42ed-911b-22429d6f9d75"
    }
  },
  "fullUrl": "urn:uuid:ab404d4b-fea2-4270-be67-1943d5e5fbd9"
}