{
  "resource": {
    "resourceType": "Organization",
    "id": "0952cfd2-d792-420d-bd68-b733027a11f1",
    "meta": {
      "lastUpdated": "2025-08-06T17:49:47-05:00"
    },
    "active": true,
    "name": "HonorHealth SSCC Boutique - Tina's Treasures",
    "address": [
      {
        "type": "physical",
        "text": "10460 N. 92nd St\nScottsdale AZ 85258\nUnited States of America",
        "line": [
          "HonorHealth SSCC Boutique - Tina's Treasures",
          "10460 N. 92nd St"
        ],
        "city": "Scottsdale",
        "state": "AZ",
        "postalCode": "85258",
        "country": "USA"
      }
    ],
    "partOf": {
      "reference": "urn:uuid:81a13344-7c78-4834-9d08-aa3d35330dc3"
    }
  },
  "fullUrl": "urn:uuid:0952cfd2-d792-420d-bd68-b733027a11f1"
}