{
  "resource": {
    "resourceType": "Organization",
    "id": "e1a42a73-0127-46a7-9a60-81f8b0eaed96",
    "meta": {
      "lastUpdated": "2025-08-26T00:05:53-05:00"
    },
    "active": true,
    "name": "Toyota I.H.S. - TMMWV",
    "address": [
      {
        "type": "physical",
        "text": "1 Sugar Maple Way\r\nBUFFALO WV 25033\r\nUnited States of America",
        "line": [
          "Toyota I.H.S. - TMMWV",
          "1 Sugar Maple Way"
        ],
        "city": "BUFFALO",
        "state": "WV",
        "postalCode": "25033",
        "country": "US"
      }
    ],
    "partOf": {
      "reference": "urn:uuid:a9983da1-cbe3-4591-aafd-016dc19675a6"
    }
  },
  "fullUrl": "urn:uuid:e1a42a73-0127-46a7-9a60-81f8b0eaed96"
}