{
  "resource": {
    "resourceType": "Organization",
    "id": "17477323-67c0-4e15-8840-212bc3eeee14",
    "meta": {
      "lastUpdated": "2025-08-06T17:50:08-05:00"
    },
    "active": true,
    "name": "ULPS N Dunlap",
    "address": [
      {
        "type": "physical",
        "text": "51 N Dunlap St\nMemphis TN 38105-4624\nUnited States of America",
        "line": [
          "ULPS N Dunlap",
          "51 N Dunlap St"
        ],
        "city": "Memphis",
        "state": "TN",
        "postalCode": "38105-4624",
        "country": "US"
      }
    ],
    "partOf": {
      "reference": "urn:uuid:fc1ec70f-06a7-4510-b329-86da06292159"
    }
  },
  "fullUrl": "urn:uuid:17477323-67c0-4e15-8840-212bc3eeee14"
}