{
  "resource": {
    "resourceType": "Organization",
    "id": "d9218200-d3ce-4c75-958a-7c70ad3c30f0",
    "meta": {
      "lastUpdated": "2025-08-06T17:50:02-05:00"
    },
    "active": true,
    "name": "Lehigh Valley Hospital - Gilbertsville",
    "address": [
      {
        "type": "physical",
        "text": "1109 Grosser Rd\nGilbertsville PA 19525-9227\nUnited States of America",
        "line": [
          "Lehigh Valley Hospital - Gilbertsville",
          "1109 Grosser Rd"
        ],
        "city": "Gilbertsville",
        "state": "PA",
        "postalCode": "19525-9227",
        "country": "US"
      }
    ],
    "partOf": {
      "reference": "urn:uuid:4a7d17c6-de0e-414b-8a62-52ae3bf98ec1"
    }
  },
  "fullUrl": "urn:uuid:d9218200-d3ce-4c75-958a-7c70ad3c30f0"
}