{
  "resource": {
    "resourceType": "Organization",
    "id": "1cfbd7ae-7625-48fd-b305-08db88783068",
    "name": "Aiyan Diabetes",
    "address": [
      {
        "line": [
          "NA"
        ],
        "city": "NA",
        "state": "NA",
        "postalCode": "NA"
      }
    ],
    "endpoint": [
      {
        "reference": "endpoint/1e79077f-0aa5-439e-ff25-08dc5fb3b230"
      }
    ]
  },
  "fullUrl": "https://app.meldrx.com/api/directories/organization/1e79077f-0aa5-439e-ff25-08dc5fb3b230"
}