{
  "resource": {
    "resourceType": "Organization",
    "id": "dbf87433-fcac-4934-a0b4-a97ef8dc779b",
    "meta": {
      "lastUpdated": "2025-08-06T17:47:34-05:00"
    },
    "active": true,
    "name": "Sea Mar- Vancouver Grand Blvd",
    "address": [
      {
        "type": "physical",
        "text": "2018 Grand Blvd\nVancouver WA 98661-2233\nUnited States",
        "line": [
          "Sea Mar- Vancouver Grand Blvd",
          "2018 Grand Blvd"
        ],
        "city": "Vancouver",
        "state": "WA",
        "postalCode": "98661-2233",
        "country": "USA"
      }
    ],
    "partOf": {
      "reference": "urn:uuid:653f5c9c-504e-4dbb-a533-4766c0593d2e"
    }
  },
  "fullUrl": "urn:uuid:dbf87433-fcac-4934-a0b4-a97ef8dc779b"
}