{
  "resource": {
    "resourceType": "Organization",
    "id": "2d48acb0-9ac2-430c-b666-f67e3f460186",
    "meta": {
      "lastUpdated": "2025-07-06T17:15:44-05:00"
    },
    "active": true,
    "name": "Connecticut Orthopaedics - Hamden - 2416 Whitney",
    "address": [
      {
        "type": "physical",
        "text": "2416 Whitney Avenue\n3rd Fl\nHamden CT 06518-3248\nUnited States of America",
        "line": [
          "Connecticut Orthopaedics - Hamden - 2416 Whitney",
          "2416 Whitney Avenue\n3rd Fl"
        ],
        "city": "Hamden",
        "state": "CT",
        "postalCode": "06518-3248",
        "country": "US"
      }
    ],
    "partOf": {
      "reference": "urn:uuid:5c1766d0-2d39-42ed-911b-22429d6f9d75"
    }
  },
  "fullUrl": "urn:uuid:2d48acb0-9ac2-430c-b666-f67e3f460186"
}