{
  "resource": {
    "resourceType": "Organization",
    "id": "4ec453f4-6c84-47a8-a15a-e26397ff323d",
    "meta": {
      "lastUpdated": "2025-08-13T00:45:06-05:00"
    },
    "active": true,
    "name": "AUSTIN HEART LAGRANGE",
    "address": [
      {
        "type": "physical",
        "text": "2 ST MARKS PLACE SUITE 160\r\nLAGRANGE TX 78945-1253\r\nUnited States of America",
        "line": [
          "AUSTIN HEART LAGRANGE",
          "2 ST MARKS PLACE SUITE 160"
        ],
        "city": "LAGRANGE",
        "state": "TX",
        "postalCode": "78945-1253",
        "country": "USA"
      }
    ],
    "partOf": {
      "reference": "urn:uuid:00b7da77-14de-4dbe-829c-e19f02ba767f"
    }
  },
  "fullUrl": "urn:uuid:4ec453f4-6c84-47a8-a15a-e26397ff323d"
}