{
  "resource": {
    "resourceType": "Organization",
    "id": "510a44fe-a92b-4b32-903c-f3dde7ec9927",
    "meta": {
      "lastUpdated": "2025-08-06T17:46:16-05:00"
    },
    "active": true,
    "name": "CPC VIGILINT",
    "address": [
      {
        "type": "physical",
        "text": "900 PERIMETER PARK DR STE G\nMORRISVILLE NC 27560\nUNITED STATES OF AMERICA",
        "line": [
          "CPC VIGILINT",
          "900 PERIMETER PARK DR STE G"
        ],
        "city": "MORRISVILLE",
        "state": "NC",
        "postalCode": "27560",
        "country": "US"
      }
    ],
    "partOf": {
      "reference": "urn:uuid:438ab062-0fc2-4b82-89e7-e9e38ba4633b"
    }
  },
  "fullUrl": "urn:uuid:510a44fe-a92b-4b32-903c-f3dde7ec9927"
}