{
  "resource": {
    "resourceType": "Organization",
    "id": "02fc9d25-22b9-4528-9218-023425faf75f",
    "meta": {
      "lastUpdated": "2025-08-06T17:50:08-05:00"
    },
    "active": true,
    "name": "UVM Health Network - CVMC Family Medicine - Berlin",
    "address": [
      {
        "type": "physical",
        "text": "246 Granger Rd, Ste 2\nBerlin VT 05602\nUnited States of America",
        "line": [
          "UVM Health Network - CVMC Family Medicine - Berlin",
          "246 Granger Rd, Ste 2"
        ],
        "city": "Berlin",
        "state": "VT",
        "postalCode": "05602",
        "country": "USA"
      }
    ],
    "partOf": {
      "reference": "urn:uuid:27fa8b63-e9b8-4930-aea0-660d878c39f5"
    }
  },
  "fullUrl": "urn:uuid:02fc9d25-22b9-4528-9218-023425faf75f"
}