{
  "resource": {
    "resourceType": "Organization",
    "id": "683bcf26-41fb-49a5-bc63-87e4146a840b",
    "meta": {
      "lastUpdated": "2025-08-06T17:47:26-05:00"
    },
    "active": true,
    "name": "Houston Methodist Orthopedics & Sports Medicine in Texas City",
    "address": [
      {
        "type": "physical",
        "text": "1310 34th St N\nTexas City TX 77590\nUnited States of America",
        "line": [
          "Houston Methodist Orthopedics & Sports Medicine in Texas City",
          "1310 34th St N"
        ],
        "city": "Texas City",
        "state": "TX",
        "postalCode": "77590",
        "country": "US"
      }
    ],
    "partOf": {
      "reference": "urn:uuid:55a2e72b-6500-45dd-ba05-d107134573c6"
    }
  },
  "fullUrl": "urn:uuid:683bcf26-41fb-49a5-bc63-87e4146a840b"
}