{
  "resource": {
    "resourceType": "Organization",
    "id": "1d9c5d58-5cc9-4f1f-8912-9986856a4247",
    "meta": {
      "lastUpdated": "2025-08-06T17:50:08-05:00"
    },
    "active": true,
    "name": "Methodist Medical Group - Primary Care Old Hwy 51",
    "address": [
      {
        "type": "physical",
        "text": "1880 Old Highway 51 S STE C\nBrighton TN 38011-8025\nUnited States of America",
        "line": [
          "Methodist Medical Group - Primary Care Old Hwy 51",
          "1880 Old Highway 51 S STE C"
        ],
        "city": "Brighton",
        "state": "TN",
        "postalCode": "38011-8025",
        "country": "US"
      }
    ],
    "partOf": {
      "reference": "urn:uuid:fc1ec70f-06a7-4510-b329-86da06292159"
    }
  },
  "fullUrl": "urn:uuid:1d9c5d58-5cc9-4f1f-8912-9986856a4247"
}