{
  "resource": {
    "resourceType": "Organization",
    "id": "c4b7935f-fcc3-467e-a3d9-813fc09d226e",
    "meta": {
      "lastUpdated": "2025-08-06T17:45:57-05:00"
    },
    "active": true,
    "name": "Mount Carmel Pulmonary & Sleep Granville",
    "address": [
      {
        "type": "physical",
        "text": "1945 Newark-Granville Rd\nGRANVILLE OH 43023-9169\nUnited States",
        "line": [
          "Mount Carmel Pulmonary & Sleep Granville",
          "1945 Newark-Granville Rd"
        ],
        "city": "GRANVILLE",
        "state": "OH",
        "postalCode": "43023-9169",
        "country": "US"
      }
    ],
    "partOf": {
      "reference": "urn:uuid:fd5eabfe-4f02-4c98-8cc5-85152d703e36"
    }
  },
  "fullUrl": "urn:uuid:c4b7935f-fcc3-467e-a3d9-813fc09d226e"
}