{
  "resource": {
    "resourceType": "Organization",
    "id": "2e4c0382-cb39-48a6-8396-40e53d77dcbd",
    "meta": {
      "lastUpdated": "2025-08-06T17:48:02-05:00"
    },
    "active": true,
    "name": "Montello Care Center SK - Geriatrics",
    "address": [
      {
        "type": "physical",
        "text": "251 Forest Lane\nMONTELLO WI 53949\nUnited States of America",
        "line": [
          "Montello Care Center SK - Geriatrics",
          "251 Forest Lane"
        ],
        "city": "MONTELLO",
        "state": "WI",
        "postalCode": "53949",
        "country": "USA"
      }
    ],
    "partOf": {
      "reference": "urn:uuid:9c4bf725-8173-4770-b91a-b0d92590403a"
    }
  },
  "fullUrl": "urn:uuid:2e4c0382-cb39-48a6-8396-40e53d77dcbd"
}