{
  "resource": {
    "resourceType": "Organization",
    "id": "9e4fa6f0-d604-4d1f-b3f4-338cba8ce2b6",
    "meta": {
      "lastUpdated": "2025-08-06T17:46:07-05:00"
    },
    "active": true,
    "name": "MaineHealth Behavioral Health at Spring Harbor Outpatient Services Lancaster St Portland",
    "address": [
      {
        "type": "physical",
        "text": "165 Lancaster St\nPortland ME 04101\nUnited States of America",
        "line": [
          "MaineHealth Behavioral Health at Spring Harbor Outpatient Services Lancaster St Portland",
          "165 Lancaster St"
        ],
        "city": "Portland",
        "state": "ME",
        "postalCode": "04101",
        "country": "USA"
      }
    ],
    "partOf": {
      "reference": "urn:uuid:f2423166-4678-4926-be66-463ce7049a80"
    }
  },
  "fullUrl": "urn:uuid:9e4fa6f0-d604-4d1f-b3f4-338cba8ce2b6"
}