{
  "resource": {
    "resourceType": "Organization",
    "id": "f278e38d-6f96-4e19-9228-9720610c07b4",
    "meta": {
      "lastUpdated": "2025-07-06T17:11:35-05:00"
    },
    "active": true,
    "name": "Quality of Life Health Services - Cullman Quality Health Care",
    "address": [
      {
        "type": "physical",
        "text": "2016 Main Street SW\nCullman AL 35055-5239\nUnited States of America",
        "line": [
          "Quality of Life Health Services - Cullman Quality Health Care",
          "2016 Main Street SW"
        ],
        "city": "Cullman",
        "state": "AL",
        "postalCode": "35055-5239",
        "country": "US"
      }
    ],
    "partOf": {
      "reference": "urn:uuid:32aea290-2d02-46c7-aaa0-e090af45f66d"
    }
  },
  "fullUrl": "urn:uuid:f278e38d-6f96-4e19-9228-9720610c07b4"
}