{
  "resource": {
    "resourceType": "Organization",
    "id": "d8d01b67-5e50-4e90-9594-a3b61b07b80b",
    "meta": {
      "lastUpdated": "2025-08-06T17:49:16-05:00"
    },
    "active": true,
    "name": "Deaconess Clinic - Pediatrics Princeton",
    "address": [
      {
        "type": "physical",
        "text": "312 THIRD AVE\nPRINCETON IN 47670-1014\nUnited States of America",
        "line": [
          "Deaconess Clinic - Pediatrics Princeton",
          "312 THIRD AVE"
        ],
        "city": "PRINCETON",
        "state": "IN",
        "postalCode": "47670-1014",
        "country": "USA"
      }
    ],
    "partOf": {
      "reference": "urn:uuid:08a79073-05e8-485d-9c1f-889732786b2b"
    }
  },
  "fullUrl": "urn:uuid:d8d01b67-5e50-4e90-9594-a3b61b07b80b"
}