{
  "resource": {
    "resourceType": "Organization",
    "id": "18ad3084-eb7f-4b0f-b77c-693dcd067b7f",
    "meta": {
      "lastUpdated": "2025-08-06T17:49:41-05:00"
    },
    "active": true,
    "name": "Bethesda Pediatrics",
    "address": [
      {
        "type": "physical",
        "text": "1350 E RICHARDS ST\nTYLER TX 75702-6153\nUnited States of America",
        "line": [
          "Bethesda Pediatrics",
          "1350 E RICHARDS ST"
        ],
        "city": "TYLER",
        "state": "TX",
        "postalCode": "75702-6153",
        "country": "USA"
      }
    ],
    "partOf": {
      "reference": "urn:uuid:3264abc4-398d-4b7f-b116-678d3fa582b5"
    }
  },
  "fullUrl": "urn:uuid:18ad3084-eb7f-4b0f-b77c-693dcd067b7f"
}