{
  "resource": {
    "resourceType": "Organization",
    "id": "4e6a96a1-7413-4f7c-974e-016a1ba72f0d",
    "identifier": [
      {
        "value": "4e6a96a1-7413-4f7c-974e-016a1ba72f0d",
        "system": "urn:oid:2.16.840.1.113883.3.3388.3.1"
      },
      {
        "value": "1184493280",
        "system": "http://hl7.org/fhir/sid/us-npi"
      },
      {
        "value": "93-3353725",
        "system": "urn:oid:2.16.840.1.113883.4.4"
      }
    ],
    "name": "Family Beginnings, LLC",
    "address": [
      {
        "line": [
          "134 Grand Avenue"
        ],
        "city": "Billings",
        "state": "MT",
        "postalCode": "59101"
      }
    ],
    "endpoint": [
      {
        "reference": "Endpoint/PatientAccess-4e6a96a1-7413-4f7c-974e-016a1ba72f0d",
        "display": "Endpoint for Patient Access"
      },
      {
        "reference": "Endpoint/ProviderSystemAccess-4e6a96a1-7413-4f7c-974e-016a1ba72f0d",
        "display": "Endpoint for Provider / System Access"
      }
    ]
  },
  "fullUrl": "urn:uuid:4e6a96a1-7413-4f7c-974e-016a1ba72f0d"
}